addscicrunch/AgeSelector.py
addscicrunch/__init__.py
addscicrunch/gui_output.py
addscicrunch/main.py
addscicrunch/static.py
addscicrunch/tacchkdlg.py
addscicrunch-1.0.0.dist-info/METADATA
addscicrunch-1.0.0.dist-info/WHEEL
addscicrunch-1.0.0.dist-info/entry_points.txt
addscicrunch-1.0.0.dist-info/top_level.txt
addscicrunch-1.0.0.dist-info/RECORD
